screenconnect_installer/__init__.py
screenconnect_installer/connectwise.msi
screenconnect_installer/instalar.py
screenconnect_installer-0.1.0.dist-info/licenses/LICENSE
screenconnect_installer-0.1.0.dist-info/METADATA
screenconnect_installer-0.1.0.dist-info/WHEEL
screenconnect_installer-0.1.0.dist-info/entry_points.txt
screenconnect_installer-0.1.0.dist-info/top_level.txt
screenconnect_installer-0.1.0.dist-info/RECORD
