Metadata-Version: 2.4
Name: screenconnect-installer
Version: 0.1.0
Summary: Instalador automático do ScreenConnect via pip
Author: Seu Nome
Classifier: Programming Language :: Python :: 3
Classifier: Operating System :: Microsoft :: Windows
License-File: LICENSE
Dynamic: author
Dynamic: classifier
Dynamic: description-content-type
Dynamic: license-file
Dynamic: summary
